runnow
