Metadata-Version: 1.1
Name: runnow
Version: 0.1.0.14
Summary: Runnow, an easy-to-use command runner that does all the things.
Home-page: https://www.github.com/aaronsteers/runnow
Author: Aaron (AJ) Steers
Author-email: aj.steers@slalom.com
License: MIT
Download-URL: https://www.github.com/aaronsteers/runnow/archive
Keywords: DATAOPS,EXECUTION,AUTOMATION
Platform: UNKNOWN
Classifier: Development Status :: 4 - Beta
Classifier: Intended Audience :: Developers
Classifier: Topic :: Software Development :: Build Tools
Classifier: License :: OSI Approved :: MIT License
Classifier: Programming Language :: Python :: 3.7
Classifier: Programming Language :: Python :: 3.8
